django_jwt/__init__.py
django_jwt/admin.py
django_jwt/decorators.py
django_jwt/exceptions.py
django_jwt/models.py
django_jwt/settings.py
django_jwt/migrations/0001_initial.py
django_jwt/migrations/0002_auto_20151227_1428.py
django_jwt/migrations/__init__.py
django_jwt/tests/__init__.py
django_jwt/tests/test_decorators.py
django_jwt/tests/test_models.py
django_jwt_expiringlinks-0.1.0.dist-info/DESCRIPTION.rst
django_jwt_expiringlinks-0.1.0.dist-info/METADATA
django_jwt_expiringlinks-0.1.0.dist-info/RECORD
django_jwt_expiringlinks-0.1.0.dist-info/WHEEL
django_jwt_expiringlinks-0.1.0.dist-info/metadata.json
django_jwt_expiringlinks-0.1.0.dist-info/top_level.txt
