Metadata-Version: 2.0
Name: django-jwt-expiringlinks
Version: 0.1.0
Summary: Django app that uses JWT to manage one-time and expiring links to protected URLs.
Home-page: https://github.com/yunojuno/django-jwt-expiringlinks
Author: Hugo Rodger-Brown
Author-email: hugo@yunojuno.com
License: UNKNOWN
Platform: UNKNOWN
Classifier: Environment :: Web Environment
Classifier: Framework :: Django
Classifier: Intended Audience :: Developers
Classifier: License :: OSI Approved :: MIT License
Classifier: Operating System :: OS Independent
Classifier: Programming Language :: Python
Classifier: Programming Language :: Python :: 2.7
Classifier: Topic :: Internet :: WWW/HTTP
Classifier: Topic :: Internet :: WWW/HTTP :: Dynamic Content
Requires-Dist: Django (>=1.8)
Requires-Dist: pyjwt
